Metadata-Version: 1.0
Name: nadima-distributions
Version: 0.2
Summary: Gaussian distributions
Home-page: UNKNOWN
Author: Nadima Dwihusna
Author-email: ndwihusn@alumni.mines.edu
License: UNKNOWN
Platform: UNKNOWN
